aspen/__init__.py
aspen/backcompat.py
aspen/exceptions.py
aspen/output.py
aspen/renderers.py
aspen/resources.py
aspen/testing.py
aspen/utils.py
aspen/http/__init__.py
aspen/http/mapping.py
aspen/http/request.py
aspen/http/resource.py
aspen/request_processor/__init__.py
aspen/request_processor/dispatcher.py
aspen/request_processor/mime.types
aspen/request_processor/typecasting.py
aspen/simplates/__init__.py
aspen/simplates/json_.py
aspen/simplates/pagination.py
aspen/simplates/simplate.py
aspen/simplates/renderers/__init__.py
aspen/simplates/renderers/json_dump.py
aspen/simplates/renderers/jsonp_dump.py
aspen/simplates/renderers/stdlib_format.py
aspen/simplates/renderers/stdlib_percent.py
aspen/simplates/renderers/stdlib_template.py
aspen-1.1.dist-info/METADATA
aspen-1.1.dist-info/WHEEL
aspen-1.1.dist-info/top_level.txt
aspen-1.1.dist-info/RECORD
