Metadata-Version: 2.1
Name: aspen
Version: 1.1
Summary: A filesystem router for Python web frameworks
Home-page: https://github.com/AspenWeb/aspen.py
Author: Chad Whitacre et al.
Author-email: team@aspen.io
License: UNKNOWN
Platform: UNKNOWN
Classifier: Development Status :: 5 - Production/Stable
Classifier: Environment :: Console
Classifier: Intended Audience :: Developers
Classifier: License :: OSI Approved :: MIT License
Classifier: Operating System :: OS Independent
Classifier: Programming Language :: Python :: 2.7
Classifier: Programming Language :: Python :: 3.5
Classifier: Programming Language :: Python :: 3.6
Classifier: Programming Language :: Python :: 3.7
Classifier: Programming Language :: Python :: 3.8
Classifier: Programming Language :: Python :: 3.9
Requires-Dist: python-mimeparse (>=0.1.4)
Requires-Dist: filesystem-tree (>=1.0.1)
Requires-Dist: six
Requires-Dist: scandir ; python_version < "3.5"
